runlike/__init__.py
runlike/inspector.py
runlike/runlike.py
runlike-1.5.1.dist-info/LICENSE.txt
runlike-1.5.1.dist-info/METADATA
runlike-1.5.1.dist-info/WHEEL
runlike-1.5.1.dist-info/entry_points.txt
runlike-1.5.1.dist-info/RECORD
